yais.py
yais-0.2.7.dist-info/entry_points.txt
yais-0.2.7.dist-info/LICENSE
yais-0.2.7.dist-info/WHEEL
yais-0.2.7.dist-info/METADATA
yais-0.2.7.dist-info/RECORD
