Metadata-Version: 2.1
Name: yais
Version: 0.2.7
Summary: Yet Another Image Scraper
Home-page: https://github.com/whtsky/yais
License: MIT
Author: Wu Haotian
Author-email: whtsky@gmail.com
Requires-Python: >=3.7,<4.0
Classifier: License :: OSI Approved :: MIT License
Classifier: Programming Language :: Python :: 3
Classifier: Programming Language :: Python :: 3.7
Classifier: Programming Language :: Python :: 3.8
Classifier: Programming Language :: Python :: 3.9
Requires-Dist: appdirs (>=1.4.4,<2.0.0)
Requires-Dist: beautifulsoup4 (>=4.8.1,<5.0.0)
Requires-Dist: cloudscraper (>=1.2.48,<2.0.0)
Requires-Dist: imagesize (>=1.2.0,<2.0.0)
Requires-Dist: requests (>=2.24.0,<3.0.0)
Project-URL: Repository, https://github.com/whtsky/yais
